infomedia/__init__.py
infomedia/__main__.py
infomedia/config.py
infomedia/run.py
infomedia/utils.py
infomedia/version.py
infomedia/dependencies/ffprobe.zip
infomedia-1.0.2.dist-info/LICENSE
infomedia-1.0.2.dist-info/METADATA
infomedia-1.0.2.dist-info/WHEEL
infomedia-1.0.2.dist-info/entry_points.txt
infomedia-1.0.2.dist-info/top_level.txt
infomedia-1.0.2.dist-info/RECORD
