Metadata-Version: 2.1
Name: infomedia
Version: 1.0.2
Summary: This is a Python application that can be used to retrieve media file information such as duration, frame rate, bit rate, etc..
Home-page: https://github.com/truethari/infomedia
Author: tharindu.dev
Author-email: tharindu.nm@yahoo.com
License: MIT
Project-URL: Source, https://github.com/truethari/infomedia/
Project-URL: Bug Tracker, https://github.com/truethari/infomedia/issues
Keywords: video ffmpeg ffprobe
Platform: UNKNOWN
Classifier: Programming Language :: Python :: 3
Classifier: License :: OSI Approved :: MIT License
Classifier: Topic :: Utilities
